graph_mate-0.1.1.dist-info/METADATA
graph_mate-0.1.1.dist-info/WHEEL
graph_mate/__init__.py
graph_mate/__init__.pyi
graph_mate/py.typed
graph_mate/graph_mate.abi3.so
graph_mate-0.1.1.dist-info/RECORD
