Metadata-Version: 2.1
Name: graph_mate
Version: 0.1.1
Classifier: Development Status :: 3 - Alpha
Classifier: Intended Audience :: Developers
Classifier: License :: OSI Approved :: MIT License
Classifier: Operating System :: OS Independent
Classifier: Programming Language :: Python
Classifier: Programming Language :: Python :: 3.8
Classifier: Programming Language :: Python :: 3.9
Classifier: Programming Language :: Python :: 3.10
Classifier: Programming Language :: Python :: 3.11
Classifier: Programming Language :: Python :: 3 :: Only
Classifier: Topic :: Software Development :: Libraries
Requires-Dist: numpy >= 1.23.0
Summary: A library of high-performant graph algorithms.
Keywords: graph,algorithms,parallel
Author: Martin Junghanns <github@s1ck.dev>, Paul Horn <developer@knutwalker.de>
Author-email: Martin Junghanns <github@s1ck.dev>, Paul Horn <developer@knutwalker.de>
License: MIT
Requires-Python: >=3.8
Project-URL: Bug Tracker, https://github.com/s1ck/graph/issues
Project-URL: Homepage, https://github.com/s1ck/graph
